bribrimapper/__init__.py
bribrimapper/data.py
bribrimapper/transcriptions.py
bribrimapper-0.0.2.dist-info/METADATA
bribrimapper-0.0.2.dist-info/WHEEL
bribrimapper-0.0.2.dist-info/licenses/AUTHORS.rst
bribrimapper-0.0.2.dist-info/licenses/LICENSE.txt
bribrimapper-0.0.2.dist-info/RECORD
