Metadata-Version: 2.3
Name: bribrimapper
Version: 0.0.2
Summary: Identification and conversion functions for Bribri text processing
Project-URL: Documentation, https://github.com/isabellahoch/bribrimapper
Project-URL: Source code, https://github.com/isabellahoch/bribrimapper
Author-email: Isabella Hochschild <isabella.e.hochschild.25@dartmouth.edu>
License-Expression: MIT
License-File: AUTHORS.rst
License-File: LICENSE.txt
Keywords: bribri,chibchan,convert,g2p,ipa,phonology,transcription
Classifier: Development Status :: 5 - Production/Stable
Classifier: Intended Audience :: Developers
Classifier: License :: OSI Approved :: MIT License
Classifier: Operating System :: OS Independent
Classifier: Programming Language :: Python
Classifier: Programming Language :: Python :: 3
Classifier: Programming Language :: Python :: 3.8
Classifier: Programming Language :: Python :: 3.9
Classifier: Programming Language :: Python :: 3.10
Classifier: Programming Language :: Python :: 3.11
Classifier: Programming Language :: Python :: 3.12
Classifier: Topic :: Software Development :: Libraries :: Python Modules
Classifier: Topic :: Text Processing :: Linguistic
Requires-Python: >=3.8
